[
  {
    "name": "Adaptive Reliability Layer",
    "url": "https://github.com/pberlizov/adaptive-reliability-layer",
    "category": "github",
    "description": ": A bounded controller for production ML under distribution shift \u2014 detects drift, learns from delayed labels, and takes the smallest safe steering step to defer unnecessary retrains",
    "source": "josephmisiti/awesome-machine-learning"
  },
  {
    "name": "Source Code",
    "url": "https://codeberg.org/inventaire/inventaires",
    "category": "tool",
    "description": ") `AGPL-3",
    "source": "awesome-selfhosted/awesome-selfhosted"
  },
  {
    "name": "plumio",
    "url": "https://plumio.app/",
    "category": "tool",
    "description": "Markdown notes taking app with live preview, document encryption, multi-user support, multi-organization capabilities and more",
    "source": "awesome-selfhosted/awesome-selfhosted"
  },
  {
    "name": "Demo",
    "url": "https://demo.plumio.app/homepage",
    "category": "tool",
    "description": ",",
    "source": "awesome-selfhosted/awesome-selfhosted"
  },
  {
    "name": "Source Code",
    "url": "https://github.com/albertasaftei/plumio",
    "category": "github",
    "description": ") `AGPL-3",
    "source": "awesome-selfhosted/awesome-selfhosted"
  }
]